hfwm/__init__.py
hfwm/core.py
hfwm/blueprints/__init__.py
hfwm/blueprints/auth.py
hfwm/blueprints/cache.py
hfwm/blueprints/config.py
hfwm/blueprints/data.py
hfwm/blueprints/development.py
hfwm/blueprints/enums.py
hfwm/blueprints/extra.py
hfwm/blueprints/large_uploads.py
hfwm/blueprints/message.py
hfwm/blueprints/perm.py
hfwm/blueprints/role.py
hfwm/blueprints/self_data.py
hfwm/blueprints/setting.py
hfwm/blueprints/sse.py
hfwm/blueprints/template.py
hfwm/blueprints/tree.py
hfwm/mains/backend.py
hfwm/mains/httpserver.py
hfwm/mains/pubsub_heart.py
hfwm/models/__init__.py
hfwm/models/api_doc.py
hfwm/models/app.py
hfwm/models/auth.py
hfwm/models/auto_page.py
hfwm/models/bind_perm.py
hfwm/models/check.py
hfwm/models/common.py
hfwm/models/make_charts.py
hfwm/models/make_check.py
hfwm/models/message.py
hfwm/models/perm.py
hfwm/models/sse.py
hfwm/models/template.py
hfwm/models/tree.py
hfwm/models/databases/__init__.py
hfwm/models/databases/handle.py
hfwm/models/databases/template.py
hfwm/models/databases/template_load.py
hfwm/test/__init__.py
hfwm/test/hfwm_client.py
hfwm/utils/__init__.py
hfwm/utils/count1000.py
hfwm/utils/intercept_after_auth.py
hfwm/utils/protocol.py
hfwm/utils/redis_url.py
hfwm/utils/response_cache.py
hfwm/utils/save_data.py
hfwm/utils/sys_env.py
hfwm-1.0.2.dist-info/licenses/LICENSE
hfwm-1.0.2.dist-info/METADATA
hfwm-1.0.2.dist-info/WHEEL
hfwm-1.0.2.dist-info/top_level.txt
hfwm-1.0.2.dist-info/RECORD
