Metadata-Version: 2.4
Name: hfwm
Version: 1.0.2
Summary: Hyper Fast Web Maker
Author: zxh
License-Expression: MIT
Project-URL: Homepage, https://github.com/zxh1993/hfwm_part
Project-URL: Repository, https://github.com/zxh1993/hfwm_part
Project-URL: Issues, https://github.com/zxh1993/hfwm_part/issues
Keywords: web,framework,fast,async
Classifier: Development Status :: 5 - Production/Stable
Classifier: Intended Audience :: Developers
Classifier: Programming Language :: Python :: 3
Classifier: Programming Language :: Python :: 3.12
Classifier: Programming Language :: Python :: 3.13
Classifier: Framework :: Flask
Classifier: Topic :: Internet :: WWW/HTTP
Classifier: Topic :: Software Development :: Libraries :: Python Modules
Requires-Python: >=3.12
License-File: LICENSE
Dynamic: license-file
